Workbook

Sheet Start Here
A1: Jackman Wheels - Ambassador Priority Order
A2: Both lists merged and run against each other | 2026-10-06 | v1 | 59 accounts scored on one model
A4: What I did
A5: Merged the 5K-25K sheet (36 accounts) and the 25K+ sheet (21 accounts), removed the 7 that appeared on both,
A6: and added 8 accounts that were sitting on the Checked and Excluded tab but actually belong in the pool.
A7: Then rescored all 59 on a single model, because the two sheets were ranked on different logic and were not comparable.
A9: Correction carried forward: @tacodust (63K) should have been on the 25K+ sheet and was not. It is in here now.
A11: How the sequence was built - working backwards
A12: The goal is selling wheels, and the constraint is that Jackman has almost no proof. No library of real installs,
A13: no roster, no track record. So the question is not who is biggest, it is what has to be true before each deal works.
A15: To land a 150K YouTube install segment, you need a product with a visible track record.
A16: To have a track record, you need a visible roster across the platforms you actually stock.
... A60: Follower counts are live as of 2026-10-06 and drift constantly.

Sheet Master List
A1: Wave | B1: Order | C1: Score | D1: Handle | E1: Name | F1: Profile URL | G1: Followers | H1: Following | I1: Ratio | J1: Location | K1: Platform | L1: Role / Content | M1: Existing Sponsors | N1: Proof | O1: Platform Gap | P1: Access | Q1: Cost Fit | R1: Buyer Intent | S1: Network | T1: Authority | U1: Conflict | V1: What to ask them for | W1: Why this position | X1: Outreach Status | Y1: Date Contacted | Z1: Response
A2: 1 | B2: 1 | C2: =ROUND('Scoring Model'!$B$4*N2+'Scoring Model'!$B$5*O2+'Scoring Model'!$B$6*P2+'Scoring Model'!$B$7*Q2+'Scoring Model'!$B$8*R2+'Scoring Model'!$B$9*S2+'Scoring Model'!$B$10*T2-'Scoring Model'!$B$11*U2,1) -> 76.5 | D2: yotawolf89 | E2: Bryan Bell | F2: https://www.instagram.com/yotawolf89/ | G2: 13400 | H2: 297 | I2: =IFERROR(G2/H2,0) -> 45.117845 | J2: San Diego, CA | K2: Toyota | L2: Professional photographer | M2: Nitto Tire; Nitto Pit Crew; Diamondback | N2: 3 | O2: 1 | P2: 2 | Q2: 3 | R2: 2 | S2: 2 | T2: =IF(I2>=50,2,IF(I2>=20,1.5,IF(I2>=10,1,IF(I2>=5,0.5,0.25)))) -> 1.5 | U2: 0 | V2: An install plus a full photo set you own outright. Collab post. Explicit rights to reuse the stills in paid social. | W2: The single highest-leverage name across both lists. You do not have a library of real installs, and he is a working photographer two hours away with a 45:1 ratio. You are buying assets and audience in one deal, at micro-tier pricing.
A3: 1 | B3: 2 | C3: =ROUND('Scoring Model'!$B$4*N3+'Scoring Model'!$B$5*O3+'Scoring Model'!$B$6*P3+'Scoring Model'!$B$7*Q3+'Scoring Model'!$B$8*R3+'Scoring Model'!$B$9*S3+'Scoring Model'!$B$10*T3-'Scoring Model'!$B$11*U3,1) -> 75.5 | D3: keepitdirty_offroad | E3: Helio Muro | F3: https://www.instagram.com/keepitdirty_offroad/ | G3: 19900 | H3: 729 | I3: =IFERROR(G3/H3,0) -> 27.297668 | J3: SoCal | K3: Ford Raptor | L3: DIY, reviews, group runs | M3: KC HiLites | N3: 2 | O3: 2 | P3: 2 | Q3: 2 | R3: 3 | S3: 2 | T3: =IF(I3>=50,2,IF(I3>=20,1.5,IF(I3>=10,1,IF(I3>=5,0.5,0.25)))) -> 1.5 | U3: 0 | V3: An install walkthrough and an honest review. Then a group run with the wheels on. | W3: Reviews and DIY mean his audience arrives already deciding what to buy. He also organises group runs, so he brings a crowd rather than just impressions. Covers Ford, which Wave 1 otherwise misses.
A4: 1 | B4: 3 | C4: =ROUND('Scoring Model'!$B$4*N4+'Scoring Model'!$B$5*O4+'Scoring Model'!$B$6*P4+'Scoring Model'!$B$7*Q4+'Scoring Model'!$B$8*R4+'Scoring Model'!$B$9*S4+'Scoring Model'!$B$10*T4-'Scoring Model'!$B$11*U4,1) -> 74.5 | D4: 22protaco | E4: Kevin | F4: https://www.instagram.com/22protaco/ | G4: 12800 | H4: 389 | I4: =IFERROR(G4/H4,0) -> 32.904884 | J4: SoCal | K4: Tacoma TRD Pro | L4: Truck build, desert | M4: None stated | N4: 2 | O4: 1 | P4: 2 | Q4: 3 | R4: 3 | S4: 2 | T4: =IF(I4>=50,2,IF(I4>=20,1.5,IF(I4>=10,1,IF(I4>=5,0.5,0.25)))) -> 1.5 | U4: 0 | V4: Straight fitment post plus wheel detail shots. Collab. | W4: Already shoots wheel close-ups unprompted - the format you want is the format he makes. 33:1 ratio on only 56 posts. One of your two originals, so the relationship is warm.
A5: 1 | B5: 4 | C5: =ROUND('Scoring Model'!$B$4*N5+'Scoring Model'!$B$5*O5+'Scoring Model'!$B$6*P5+'Scoring Model'!$B$7*Q5+'Scoring Model'!$B$8*R5+'Scoring Model'!$B$9*S5+'Scoring Model'!$B$10*T5-'Scoring Model'!$B$11*U5,1) -> 74.5 | D5: ghostpro.la | E5: Randy Apigo | F5: https://www.instagram.com/ghostpro.la/ | G5: 35400 | H5: 846 | I5: =IFERROR(G5/H5,0) -> 41.843972 | J5: Los Angeles, CA | K5: 2026 Tacoma TRD Pro | L5: Professional photographer | M5: Nitto Tire; KC HiLites | N5: 3 | O5: 1 | P5: 3 | Q5: 1 | R5: 2 | S5: 2 | T5: =IF(I5>=50,2,IF(I5>=20,1.5,IF(I5>=10,1,IF(I5>=5,0.5,0.25)))) -> 1.5 | U5: 0 | V5: Paid shoot first, ambassador second. Catalogue-grade photography on a current-year truck. | W5: The only public email across 59 accounts, so the lowest-friction first contact you have. Current-year Tacoma and a professional camera. Costs more than the rest of Wave 1 and is worth it for the asset library alone.
A6: 1 | B6: 5 | C6: =ROUND('Scoring Model'!$B$4*N6+'Scoring Model'!$B$5*O6+'Scoring Model'!$B$6*P6+'Scoring Model'!$B$7*Q6+'Scoring Model'!$B$8*R6+'Scoring Model'!$B$9*S6+'Scoring Model'!$B$10*T6-'Scoring Model'!$B$11*U6,1) -> 73 | D6: groovyrunner.gx | E6: W I L L | F6: https://www.instagram.com/groovyrunner.gx/ | G6: 20700 | H6: 1307 | I6: =IFERROR(G6/H6,0) -> 15.837796 | J6: Orange County, CA | K6: 4Runner TRD Pro + Lexus GX550 | L6: Builds, overland | M6: KC HiLites; Nitto Pit Crew; Rago Fab; C4 Fab | N6: 2 | O6: 2 | P6: 2 | Q6: 2 | R6: 3 | S6: 2 | T6: =IF(I6>=50,2,IF(I6>=20,1.5,IF(I6>=10,1,IF(I6>=5,0.5,0.25)))) -> 1 | U6: 0 | V6: Two fitments off one agreement - one per rig. Staggered a month apart. | W6: Two vehicles means two sets of fitment content from a single relationship, which is the best content-per-dollar on the list. Already runs multiple brand partnerships, so he knows the cadence.
A7: 1 | B7: 6 | C7: =ROUND('Scoring Model'!$B$4*N7+'Scoring Model'!$B$5*O7+'Scoring Model'!$B$6*P7+'Scoring Model'!$B$7*Q7+'Scoring Model'!$B$8*R7+'Scoring Model'!$B$9*S7+'Scoring Model'!$B$10*T7-'Scoring Model'!$B$11*U7,1) -> 69.5 | D7: trdle_pwr | E7: Vic | F7: https://www.instagram.com/trdle_pwr/ | G7: 11900 | H7: 421 | I7: =IFERROR(G7/H7,0) -> 28.266033 | J7: Orange County, CA | K7: 2022 4Runner TRD Pro | L7: Builds, adventure | M7: Openroad 4WD | N7: 2 | O7: 1 | P7: 2 | Q7: 3 | R7: 2 | S7: 2 | T7: =IF(I7>=50,2,IF(I7>=20,1.5,IF(I7>=10,1,IF(I7>=5,0.5,0.25)))) -> 1.5 | U7: 0 | V7: Fitment post plus Story set. Collab. | W7: Orange County, inside the same #toyotasocal circle as the rest of Wave 1. Cheap, clean 28:1 ratio, low sponsor load. He is here partly so the cluster sees four of its own sign at once.
A8: 1 | B8: 7 | C8: =ROUND('Scoring Model'!$B$4*N8+'Scoring Model'!$B$5*O8+'Scoring Model'!$B$6*P8+'Scoring Model'!$B$7*Q8+'Scoring Model'!$B$8*R8+'Scoring Model'!$B$9*S8+'Scoring Model'!$B$10*T8-'Scoring Model'!$B$11*U8,1) -> 64.5 | D8: campygilmore | E8: Jose Fernandez | F8: https://www.instagram.com/campygilmore/ | G8: 13600 | H8: 1857 | I8: =IFERROR(G8/H8,0) -> 7.3236403 | J8: Orange County, CA | K8: 2024 Tacoma | L8: Overland, camping, fishing | M8: None stated | N8: 2 | O8: 1 | P8: 2 | Q8: 3 | R8: 2 | S8: 2 | T8: =IF(I8>=50,2,IF(I8>=20,1.5,IF(I8>=10,1,IF(I8>=5,0.5,0.25)))) -> 0.5 | U8: 0 | V8: Fitment post plus a trail set. Collab. Ask him who else should be in the room. | W8: Scores slightly below the rest of Wave 1 on ratio alone, but he is your original seed, he is local, and the entire SoCal cluster traces back through him. Treat him as the anchor and the introduction route, not just a placement.
A9: 2 | B9: 8 | C9: =ROUND('Scoring Model'!$B$4*N9+'Scoring Model'!$B$5*O9+'Scoring Model'!$B$6*P9+'Scoring Model'!$B$7*Q9+'Scoring Model'!$B$8*R9+'Scoring Model'!$B$9*S9+'Scoring Model'!$B$10*T9-'Scoring Model'!$B$11*U9,1) -> 72 | D9: zr2chris22 | E9: ZR2Chris | F9: https://www.instagram.com/zr2chris22/ | G9: 22400 | H9: 1527 | I9: =IFERROR(G9/H9,0) -> 14.669286 | J9: Unknown | K9: 2022 Silverado ZR2 | L9: Off-road, builds | M9: Nitto Tire; KC HiLites | N9: 2 | O9: 3 | P9: 1 | Q9: 2 | R9: 3 | S9: 2 | T9: =IF(I9>=50,2,IF(I9>=20,1.5,IF(I9>=10,1,IF(I9>=5,0.5,0.25)))) -> 1 | U9: 0 | V9: Fitment post, plus put wheels in front of his wheeling group. | W9: The best Chevy option that exists above 20K, and Chevy is nearly empty at this tier. He also owns @foosgonewheeling, so he brings an organised group. Highest-scoring non-SoCal name.
A10: 2 | B10: 9 | C10: =ROUND('Scoring Model'!$B$4*N10+'Scoring Model'!$B$5*O10+'Scoring Model'!$B$6*P10+'Scoring Model'!$B$7*Q10+'Scoring Model'!$B$8*R10+'Scoring Model'!$B$9*S10+'Scoring Model'!$B$10*T10-'Scoring Model'!$B$11*U10,1) -> 71.5 | D10: trailmammoth | E10: (no name given) | F10: https://www.instagram.com/trailmammoth/ | G10: 11400 | H10: 228 | I10: =IFERROR(G10/H10,0) -> 50 | J10: Unknown | K10: 2025 4Runner + 2026 Tacoma | L10: Builds, YouTube | M10: None stated | N10: 2 | O10: 2 | P10: 1 | Q10: 3 | R10: 3 | S10: 1 | T10: =IF(I10>=50,2,IF(I10>=20,1.5,IF(I10>=10,1,IF(I10>=5,0.5,0.25)))) -> 2 | U10: 0 | V10: Fitment on both current builds. Ask for the YouTube cut as well as the grid post. | W10: 50:1 ratio, the best in the micro tier, and he is building on the two newest platforms Toyota sells. Getting on a 2026 Tacoma early is worth more than the follower count suggests.
A11: 2 | B11: 10 | C11: =ROUND('Scoring Model'!$B$4*N11+'Scoring Model'!$B$5*O11+'Scoring Model'!$B$6*P11+'Scoring Model'!$B$7*Q11+'Scoring Model'!$B$8*R11+'Scoring Model'!$B$9*S11+'Scoring Model'!$B$10*T11-'Scoring Model'!$B$11*U11,1) -> 69.5 | D11: familycruiser250 | E11: Ryan Medes | F11: https://www.instagram.com/familycruiser250/ | G11: 9628 | H11: 1604 | I11: =IFERROR(G11/H11,0) -> 6.0024938 | J11: SoCal | K11: Land Cruiser LC250 | L11: Overland, family, photography | M11: Club Two Fifty | N11: 2 | O11: 2 | P11: 2 | Q11: 3 | R11: 2 | S11: 2 | T11: =IF(I11>=50,2,IF(I11>=20,1.5,IF(I11>=10,1,IF(I11>=5,0.5,0.25)))) -> 0.5 | U11: 0 | V11: LC250 fitment. He sells content services, so negotiate the photo rights up front. | W11: LC250 is a fresh platform with thin aftermarket coverage, and he runs the Club Two Fifty community. SoCal. Bio says DM for content, so expect a quote rather than a trade.
A12: 2 | B12: 11 | C12: =ROUND('Scoring Model'!$B$4*N12+'Scoring Model'!$B$5*O12+'Scoring Model'!$B$6*P12+'Scoring Model'!$B$7*Q12+'Scoring Model'!$B$8*R12+'Scoring Model'!$B$9*S12+'Scoring Model'!$B$10*T12-'Scoring Model'!$B$11*U12,1) -> 68.5 | D12: chance.the.raptr | E12: Chance | F12: https://www.instagram.com/chance.the.raptr/ | G12: 37500 | H12: 674 | I12: =IFERROR(G12/H12,0) -> 55.637982 | J12: Unknown | K12: 2024 Bronco Raptor | L12: Build, off-road | M12: Nitto Pit Crew; ADD Offroad | N12: 2 | O12: 3 | P12: 1 | Q12: 1 | R12: 3 | S12: 1 | T12: =IF(I12>=50,2,IF(I12>=20,1.5,IF(I12>=10,1,IF(I12>=5,0.5,0.25)))) -> 2 | U12: 0 | V12: Fitment on the Bronco Raptor. Lead with the fact that almost nobody makes a proper fitment for it yet. | W12: Bronco Raptor is a halo platform with very little aftermarket wheel competition. 56:1 ratio and an existing Nitto Pit Crew member. This is a land-grab, not a placement.
A13: 2 | B13: 12 | C13: =ROUND('Scoring Model'!$B$4*N13+'Scoring Model'!$B$5*O13+'Scoring Model'!$B$6*P13+'Scoring Model'!$B$7*Q13+'Scoring Model'!$B$8*R13+'Scoring Model'!$B$9*S13+'Scoring Model'!$B$10*T13-'Scoring Model'!$B$11*U13,1) -> 66.5 | D13: soka._.boka | E13: oshu | F13: https://www.instagram.com/soka._.boka/ | G13: 9080 | H13: 871 | I13: =IFERROR(G13/H13,0) -> 10.424799 | J13: Phoenix, AZ | K13: 2023 Bronco Badlands | L13: Builds, overland | M13: KC HiLites | N13: 2 | O13: 2 | P13: 1 | Q13: 3 | R13: 3 | S13: 1 | T13: =IF(I13>=50,2,IF(I13>=20,1.5,IF(I13>=10,1,IF(I13>=5,0.5,0.25)))) -> 1 | U13: 0 | V13: Fitment post. His audience will ask clearance questions - make sure he has the answers. | W13: Has a highlight called Fit 35s on 4G. His followers are there specifically for fitment problems, which is the most qualified traffic on the list. Covers Bronco cheaply.
... A60: Hold | B60: 59 | C60: =ROUND('Scoring Model'!$B$4*N60+'Scoring Model'!$B$5*O60+'Scoring Model'!$B$6*P60+'Scoring Model'!$B$7*Q60+'Scoring Model'!$B$8*R60+'Scoring Model'!$B$9*S60+'Scoring Model'!$B$10*T60-'Scoring Model'!$B$11*U60,1) -> 9 | D60: adriian_huerta | E60: (no name given) | F60: https://www.instagram.com/adriian_huerta/ | G60: 33600 | H60: 2250 | I60: =IFERROR(G60/H60,0) -> 14.933333 | J60: Unknown | K60: Unknown | L60: Unknown | M60: Unknown | N60: 0 | O60: 0 | P60: 0 | Q60: 1 | R60: 0 | S60: 0 | T60: =IF(I60>=50,2,IF(I60>=20,1.5,IF(I60>=10,1,IF(I60>=5,0.5,0.25)))) -> 1 | U60: 0 | V60: Do not spend until a human reviews the feed and comments. | W60: 33.6K followers and a completely empty bio - no name, no location, no rig. Lowest ratio of any large account at 15:1. Unverifiable from the outside.
A62: Blue columns (Proof through Conflict) are the judgement inputs. Change any of them and Score, and the order, follow.
A63: Score = 7*Proof + 5*Platform Gap + 6*Access + 4*Cost Fit + 5*Buyer Intent + 4.5*Network + 5*Authority - 25*Conflict. Maximum 100.
A64: Authority is derived from the follower/following ratio - it is a formula, not a judgement call.
A65: Sorted by wave, then by score within each wave. Outreach Status, Date Contacted and Response are yours.
A66: Source: all 59 profiles read live on Instagram. The 25K+ accounts and all carry-overs were re-read 2026-10-06; the micro-tier accounts were read 2026-09-16.

Sheet Scoring Model
A1: Unified scoring model - both lists, one scale
A2: Edit any blue weight and every Score and the whole running order on Master List recalculates.
A4: Proof value (x0-3) | B4: 7 | C4: Will this produce a usable install or photo asset? A working photographer scores 3. Jackman's biggest content gap.
A5: Platform gap (x0-3) | B5: 5 | C5: Rarity-weighted. Ram, GMC, Chevy and Tundra score 3 because almost nobody covers them. Tacoma and 4Runner score 1 - saturated.
A6: Access (x0-3) | B6: 6 | C6: SoCal plus a public contact scores 3. Physical reach matters for installs and shoots even now the Expo has passed.
A7: Cost fit (x0-3) | B7: 4 | C7: Under 15K scores 3 - a product deal is realistic. Over 70K scores 0 - that is a rate card.
A8: Buyer intent (x0-3) | B8: 5 | C8: Is the audience mid-build and about to spend, or watching for entertainment? Build and tech accounts score 3, comedy and art score 0.
A9: Network effect (x0-2) | B9: 4.5 | C9: Brings a group, an event, a shop, or sits inside the SoCal cluster where signings compound.
A10: Authority (x0-2) | B10: 5 | C10: Derived from follower/following ratio, not judged. High ratio means people sought them out.
A11: Conflict penalty | B11: 25 | C11: Subtracted when they already run a competing WHEEL brand. Tires, lighting and suspension do not conflict.
A13: Maximum possible score | B13: =B4*3+B5*3+B6*3+B7*3+B8*3+B9*2+B10*2 -> 100
A15: Reach floor: 5,000 followers. Accounts below it are routed to the Develop wave rather than scored out, because on some platforms nobody clears the floor.

Sheet Dealer and Partner Track
A1: Parallel track - these are not ambassadors
A2: Shops, groups and events found across both scans. They belong in the dealer pipeline and the events calendar, not the ambassador budget.
A4: Handle | B4: Name | C4: Followers | D4: Location | E4: What they are | F4: Why it matters
A5: runnin4tacos | B5: Runnin 4 Tacos | C5: 126000 | D5: Denver, CO | E5: Toyota parts store + install shop | F5: Strongest dealer lead on either list. 126K followers attached to a real install bay. Pairs naturally with @littletruckbigworld, also Denver.
A6: thekietco | B6: The Kiet Co | C6: - | D6: Unknown | E6: Fabrication shop | F6: Owned by @brodi_wodie (Wave 3). One conversation covers creator and shop.
A7: foosgonewheeling | B7: Foos Gone Wheeling | C7: - | D7: Unknown | E7: Wheeling group | F7: Owned by @zr2chris22 (Wave 2). Event and group-run partner.
A8: thewheelshopinc | B8: The Wheel Shop Inc | C8: - | D8: Unknown | E8: Wheel retailer | F8: Does the install work for @bad_at4x. Direct dealer lead.
A9: koritastires | B9: Koritas Off-Road | C9: - | D9: Unknown | E9: Lift kits, wheels, tires | F9: Sells wheels. Direct dealer lead.
A10: ltwmotorsports | B10: LTW Motorsports | C10: - | D10: Unknown | E10: Lift kits, tires, wheels | F10: Sells wheels. Direct dealer lead.
A11: mesocustoms | B11: MESO Customs LLC | C11: - | D11: Unknown | E11: Toyota accessories | F11: Co-marketing rather than dealer.
A13: EVENT, with a deadline: @395jnky runs Overlanding for Warriors, Nov 13-15 2026, Eastern Sierra, benefiting wounded veterans. Five weeks out. Sponsorship, not an ambassador deal.
A14: EVENT: @poorboyraptor runs Arizona Raptor Runs, 7th edition. @zr2chris22 runs Foos Gone Wheeling. Both bring an organised group with them.
A16: Source: public Instagram profiles, read 2026-09-16 and 2026-10-06.
